{
    "activityLevel": {
        "1": [
            "Dignified",
            "Docile",
            "Gentle",
            "Reserved",
            "Calm",
            "Good-tempered",
            "Quiet",
            "Tolerant"
        ],
        "2": [
            "Independent",
            "Docile",
            "Gentle",
            "Reserved",
            "Steady",
            "Calm",
            "Good-tempered",
            "Easygoing",
            "Adaptable",
            "Quiet",
            "Patient",
            "Cooperative"
        ],
        "3": [
            "Playful",
            "Adventurous",
            "Outgoing",
            "Steady",
            "Spirited",
            "Excitable",
            "Feisty",
            "Quick",
            "Sociable",
            "Athletic",
            "Bubbly",
            "Spunky"
        ],
        "4": [
            "Adventurous",
            "Outgoing",
            "Energetic",
            "Tenacious",
            "Lively",
            "Rugged",
            "Agile",
            "Excitable",
            "Hard-working",
            "Quick",
            "Powerful",
            "Athletic",
            "Fast"
        ],
        "5": [
            "Active",
            "Adventurous",
            "Wild",
            "Outgoing",
            "Energetic",
            "Tenacious",
            "Lively",
            "Fierce",
            "Agile",
            "Excitable",
            "Hard-working",
            "Powerful",
            "Athletic",
            "Boisterous",
            "Fast"
        ]
    },
    "childFriendly": {
        "yes": [
            "Playful",
            "Adventurous",
            "Active",
            "Fun-loving",
            "Clownish",
            "Happy",
            "Dutiful",
            "Outgoing",
            "Friendly",
            "Loyal",
            "Docile",
            "Receptive",
            "Faithful",
            "Loving",
            "Responsible",
            "Gentle",
            "Affectionate",
            "Devoted",
            "Obedient",
            "Kind",
            "Sweet-Tempered",
            "Steady",
            "Good-natured",
            "Companionable",
            "Even Tempered",
            "Amiable",
            "Hardy",
            "Calm",
            "Good-tempered",
            "Cheerful",
            "Easygoing",
            "Trusting",
            "Lovable",
            "Stable",
            "Quiet",
            "Sociable",
            "Patient",
            "Great-hearted",
            "Tolerant",
            "Cooperative",
            "Trustworthy",
            "Respectful",
            "Thoughtful",
            "Generous",
            "Sturdy",
            "Diligent"
        ],
        "no": [
            "Aloof",
            "Stubborn",
            "Dignified",
            "Independent",
            "Wild",
            "Energetic",
            "Assertive",
            "Dominant",
            "Strong Willed",
            "Reserved",
            "Tenacious",
            "Bold",
            "Fearless",
            "Lively",
            "Cautious",
            "Spirited",
            "Rugged",
            "Fierce",
            "Excitable",
            "Determined",
            "Watchful",
            "Feisty",
            "Sensitive",
            "Powerful",
            "Strong",
            "Suspicious",
            "Mischievous",
            "Bossy",
            "Cunning",
            "Boisterous",
            "Cat-like",
            "Aggressive",
            "Willful",
            "Fast"
        ]
    },
    "sizes": {
        "toy": 25,
        "small": 38,
        "medium": 50,
        "large": 51,
        "no preference": 999
    },
    "purpose": {
        "general": [
            "Playful",
            "Fun-loving",
            "Happy",
            "Outgoing",
            "Friendly",
            "Loyal",
            "Faithful",
            "Loving",
            "Trainable",
            "Responsible",
            "Affectionate",
            "Devoted",
            "Kind",
            "Sweet-Tempered",
            "Attentive",
            "Steady",
            "Good-natured",
            "Spirited",
            "Companionable",
            "Even Tempered",
            "Joyful",
            "Amiable",
            "Calm",
            "Good-tempered",
            "Cheerful",
            "Easygoing",
            "Adaptable",
            "Trusting",
            "Lovable",
            "Stable",
            "Sociable",
            "Great-hearted",
            "Tolerant",
            "People-Oriented",
            "Trustworthy",
            "Respectful",
            "Thoughtful",
            "Generous",
            "Bubbly",
            "Extroverted",
            "Charming",
            "Spunky"
        ],
        "guarding": [
            "Stubborn",
            "Curious",
            "Independent",
            "Dutiful",
            "Alert",
            "Confident",
            "Intelligent",
            "Courageous",
            "Loyal",
            "Brave",
            "Composed",
            "Receptive",
            "Protective",
            "Trainable",
            "Responsible",
            "Assertive",
            "Dominant",
            "Strong Willed",
            "Obedient",
            "Bold",
            "Reliable",
            "Fearless",
            "Fierce",
            "Agile",
            "Determined",
            "Self-confidence",
            "Watchful",
            "Territorial",
            "Bright",
            "Powerful",
            "Strong",
            "Suspicious",
            "Bossy",
            "Cunning",
            "Self-important",
            "Aggressive",
            "Unflappable",
            "Diligent",
            "Vigilant"
        ],
        "working": [
            "Hardworking",
            "Active",
            "Dignified",
            "Independent",
            "Dutiful",
            "Outgoing",
            "Alert",
            "Confident",
            "Intelligent",
            "Courageous",
            "Loyal",
            "Brave",
            "Receptive",
            "Faithful",
            "Trainable",
            "Energetic",
            "Obedient",
            "Tenacious",
            "Steady",
            "Bold",
            "Fearless",
            "Lively",
            "Spirited",
            "Rugged",
            "Refined",
            "Agile",
            "Determined",
            "Self-confidence",
            "Hardy",
            "Watchful",
            "Hard-working",
            "Bright",
            "Quick",
            "Inquisitive",
            "Strong",
            "Cunning",
            "Athletic",
            "Cooperative",
            "Sturdy",
            "Clever",
            "Unflappable",
            "Vigilant"
        ],
        "companion": [
            "Adventurous",
            "Dignified",
            "Happy",
            "Dutiful",
            "Friendly",
            "Courageous",
            "Loyal",
            "Composed",
            "Receptive",
            "Faithful",
            "Loving",
            "Affectionate",
            "Devoted",
            "Kind",
            "Sweet-Tempered",
            "Attentive",
            "Reliable",
            "Companionable",
            "Even Tempered",
            "Joyful",
            "Amiable",
            "Calm",
            "Good-tempered",
            "Sensitive",
            "Trusting",
            "Lovable",
            "Stable",
            "Tolerant",
            "People-Oriented",
            "Cooperative",
            "Respectful",
            "Thoughtful",
            "Generous",
            "Clever",
            "Bubbly",
            "Unflappable",
            "Vigilant"
        ]
    }
}